django_blog/__init__.py
django_blog/admin.py
django_blog/apps.py
django_blog/forms.py
django_blog/models.py
django_blog/tests.py
django_blog/urls.py
django_blog/views.py
django_blog/migrations/0001_initial.py
django_blog/migrations/0002_useraddress.py
django_blog/migrations/0003_alter_useraddress_table.py
django_blog/migrations/0004_alter_useraddress_table.py
django_blog/migrations/0005_alter_useraddress_table.py
django_blog/migrations/0006_progress_alter_useraddress_table.py
django_blog/migrations/0007_remove_progress_percentagedownload_and_more.py
django_blog/migrations/__init__.py
django_vector_sense_blog-1.0.dist-info/LICENSE
django_vector_sense_blog-1.0.dist-info/METADATA
django_vector_sense_blog-1.0.dist-info/WHEEL
django_vector_sense_blog-1.0.dist-info/top_level.txt
django_vector_sense_blog-1.0.dist-info/RECORD
