Metadata-Version: 2.1
Name: django-vector-sense-blog
Version: 1.0
Summary: Geocoder Vector Sense
Home-page: https://github.com/your_username/django_blog
Author: Malaika
Author-email: malaikaseher5@gmail.com
Classifier: Environment :: Web Environment
Classifier: Framework :: Django
Classifier: Operating System :: OS Independent
Classifier: Programming Language :: Python :: 3
Classifier: Programming Language :: Python :: 3 :: Only
Classifier: Programming Language :: Python :: 3.5
Classifier: Programming Language :: Python :: 3.6
Classifier: Programming Language :: Python :: 3.7
Classifier: Programming Language :: Python :: 3.8
Classifier: Topic :: Software Development :: Libraries :: Python Modules
Requires-Python: >=3.5
License-File: LICENSE
